LICENSE
README.md
setup.py
cowayaio/__init__.py
cowayaio/__version__.py
cowayaio/constants.py
cowayaio/coway_client.py
cowayaio/exceptions.py
cowayaio/purifier_model.py
cowayaio/str_enum.py
cowayaio.egg-info/PKG-INFO
cowayaio.egg-info/SOURCES.txt
cowayaio.egg-info/dependency_links.txt
cowayaio.egg-info/requires.txt
cowayaio.egg-info/top_level.txt