Metadata-Version: 2.1
Name: cowayaio
Version: 0.2.4
Summary: A asynchronous python library for Coway Air Purifiers 
Home-page: https://github.com/RobertD502/cowayaio
Author: Robert Drinovac
Author-email: unlisted@gmail.com
License: UNKNOWN
Project-URL: Bug Reports, https://github.com/RobertD502/cowayaio/issues
Project-URL: Source, https://github.com/RobertD502/cowayaio/
Keywords: coway,iocare,iocare api,coway api,airmega
Platform: UNKNOWN
Classifier: Programming Language :: Python :: 3
Classifier: License :: OSI Approved :: MIT License
Classifier: Operating System :: OS Independent
Requires-Python: >=3.8
